su2gui/JsonSchema.json
su2gui/__init__.py
su2gui/cli.py
su2gui/su2_validation_schema.json
su2gui/su2gui.py
su2gui/su2gui_cli.py
su2gui/core/__init__.py
su2gui/core/config_validator.py
su2gui/core/json_validation.py
su2gui/core/logger.py
su2gui/core/pipeline.py
su2gui/core/solver.py
su2gui/core/su2_io.py
su2gui/core/su2_json.py
su2gui/core/su2_py_wrapper.py
su2gui/core/user_config.py
su2gui/core/variables.py
su2gui/icons/abacus.svg
su2gui/icons/chevron-down.svg
su2gui/icons/chevron-up.svg
su2gui/icons/trash-can-outline.svg
su2gui/icons/unfold-less-horizontal.svg
su2gui/img/favicon.ico
su2gui/img/logoSU2small.png
su2gui/img/material.jpg
su2gui/img/overview_su2gui.png
su2gui/installer/__init__.py
su2gui/installer/build.py
su2gui/installer/conda.py
su2gui/installer/constants.py
su2gui/installer/detect.py
su2gui/installer/detect_temp.py
su2gui/installer/env.py
su2gui/installer/fetch.py
su2gui/installer/ui.py
su2gui/ui/__init__.py
su2gui/ui/boundaries.py
su2gui/ui/cases.py
su2gui/ui/config.py
su2gui/ui/fileio.py
su2gui/ui/initialization.py
su2gui/ui/materials.py
su2gui/ui/mesh.py
su2gui/ui/monitor.py
su2gui/ui/numerics.py
su2gui/ui/physics.py
su2gui/ui/schema_manager.py
su2gui/ui/uicard.py
su2gui/ui/variables.py
su2gui/ui/vtk_helper.py
su2gui/user/config.json
su2gui/user/history.csv
su2gui-1.0.2.dist-info/licenses/LICENSE.txt
su2gui-1.0.2.dist-info/METADATA
su2gui-1.0.2.dist-info/WHEEL
su2gui-1.0.2.dist-info/entry_points.txt
su2gui-1.0.2.dist-info/top_level.txt
su2gui-1.0.2.dist-info/RECORD
